[
  {
    "_id": "nCFm",
    "title": "Ant invasion",
    "description": "Trail of ants marching across the kitchen counter",
    "severity": 2,
    "createdAt": 1764679126757,
    "labels": [
      "ant",
      "home"
    ]
  },
  {
    "_id": "nKfp",
    "title": "Spider in the shower",
    "description": "Big spider chilling in the corner of the shower",
    "severity": 4,
    "createdAt": 1764679126757,
    "labels": [
      "spider",
      "bathroom"
    ]
  },
  {
    "_id": "WOez",
    "title": "Bug 1764679589277",
    "severity": 3,
    "createdAt": "2025-12-02T12:46:31.145Z",
    "labels": []
  },
  {
    "_id": "DnfF",
    "title": "cocorouch",
    "description": "worst bug ever (by zoe)",
    "severity": 10,
    "createdAt": "2025-12-02T12:47:36.179Z",
    "labels": [
      "critical",
      "dangerous"
    ]
  }
]